./.gitignore
./LICENSE
./PKG-INFO
./README.md
./pyproject.toml
./htmxido/__init__.py
./htmxido/htmx.py
htmxido-0.2.0.dist-info/METADATA
htmxido-0.2.0.dist-info/WHEEL
htmxido-0.2.0.dist-info/licenses/LICENSE
htmxido-0.2.0.dist-info/RECORD
