Metadata-Version: 2.1
Name: htmxido
Version: 0.2.0
Summary: A Python library to generate HTMX/HTML
Project-URL: Homepage, https://github.com/maxpert/htmxido
Project-URL: Issues, https://github.com/maxpert/htmxido/issues
Author-email: Zohaib Sibte Hassan <zohaibsh@gmail.com>
License-File: LICENSE
Classifier: License :: OSI Approved :: MIT License
Classifier: Operating System :: OS Independent
Classifier: Programming Language :: Python :: 3
Classifier: Topic :: Text Processing :: Markup :: HTML
Requires-Python: >=3.6
